LICENSE
MANIFEST.in
README.md
requirements.txt
setup.py
ironworker/__init__.py
ironworker/__version__.py
ironworker/core.py
ironworker/ziputil.py
ironworker.egg-info/PKG-INFO
ironworker.egg-info/SOURCES.txt
ironworker.egg-info/dependency_links.txt
ironworker.egg-info/requires.txt
ironworker.egg-info/top_level.txt