Metadata-Version: 1.0
Name: ironworker
Version: 0.0.4
Summary: Python Interface to Iron.io Worker API
Home-page: https://github.com/hsdp/python-ironworker
Author: Adam Jaso
Author-email: ajaso@hsdp.io
License: Apache License Version 2.0
Platform: UNKNOWN
